LICENSE.txt
MANIFEST.in
Notice.txt
README.rst
setup.py
Doc/index.html
Doc/index.rst
Examples/IPNotebooks/00 Using ZEMAX and PyZDDE with IPython notebook.ipynb
Examples/IPNotebooks/01 Notes on ipzCaptureWindow functions.ipynb
Examples/IPNotebooks/02 Simple fiber coupling analysis using Zemax's POP.ipynb
Examples/IPNotebooks/03 Generation of Speckle using Zemax Grid Sag Surface.ipynb
Examples/IPNotebooks/04 Acquisition and analysis Image Simulation data from Zemax.ipynb
Examples/Misc/parityAndSpeedTestOfArrayTracingFuncs.py
Examples/Scripts/arrayTraceNSCdemo.py
Examples/Scripts/arrayTraceOutput.txt
Examples/Scripts/arrayTraceSimple.py
Examples/Scripts/beamFileRead.py
Examples/Scripts/beamFileWrite.py
Examples/Scripts/blankFile.py
Examples/Scripts/concentricSpheres.py
Examples/Scripts/coupEffSgleModePOPEx.CFG
Examples/Scripts/couplingEfficiencySingleModeFibers.py
Examples/Scripts/pikachu2.png
Examples/Scripts/pikachu2.zbf
Examples/Scripts/plotSpiralSpot.py
Examples/Scripts/plotSpiralSpotUsingArrayTrace.py
Examples/Scripts/searchLargestHiatusLens.py
Examples/Scripts/type2spdc.zbf
PyZDDE.egg-info/PKG-INFO
PyZDDE.egg-info/SOURCES.txt
PyZDDE.egg-info/dependency_links.txt
PyZDDE.egg-info/top_level.txt
ZMXFILES/ConcentricSpheres.SES
ZMXFILES/ConcentricSpheres.zmx
ZMXFILES/Cooke_40_degree_field.zmx
ZMXFILES/Cooke_40_degree_field_PreSettings_OnlyCardinals.CFG
ZMXFILES/Cooke_40_degree_field_unittest.CFG
ZMXFILES/Double_Gauss_5_degree field.ZMX
ZMXFILES/Doublet.ZMX
ZMXFILES/Fiber_Coupling.ZMX
ZMXFILES/Fiber_Coupling_POPunittest.CFG
ZMXFILES/Fiber_Coupling_POPunittest_Irradiance.CFG
ZMXFILES/Fiber_Coupling_POPunittest_NoFiberCompute.CFG
ZMXFILES/Fiber_Coupling_POPunittest_Phase.CFG
ZMXFILES/Information.txt
ZMXFILES/LENS.SES
ZMXFILES/LENS.ZMX
ZMXFILES/RESET_SETTINGS_DVW.CFG
ZMXFILES/RESET_SETTINGS_FFTMTF.CFG
ZMXFILES/RESET_SETTINGS_FFTPSF.CFG
ZMXFILES/RESET_SETTINGS_FFTPSFCS.CFG
ZMXFILES/RESET_SETTINGS_HUYGENSMTF.CFG
ZMXFILES/RESET_SETTINGS_HUYGENSPSF.CFG
ZMXFILES/RESET_SETTINGS_HUYGENSPSFCS.CFG
ZMXFILES/RESET_SETTINGS_IMGSIM.CFG
ZMXFILES/RESET_SETTINGS_POP_IRR.CFG
