Metadata-Version: 1.1
Name: PyZDDE
Version: 2.0.3
Summary: Zemax / OpticStudio standalone extension using Python
Home-page: https://github.com/indranilsinharoy/PyZDDE
Author: Indranil Sinharoy
Author-email: indranil_leo@yahoo.com
License: MIT
Keywords: zemax opticstudio extensions dde optics
Platform: UNKNOWN
Classifier: Development Status :: 5 - Production/Stable
Classifier: Intended Audience :: Science/Research
Classifier: Natural Language :: English
Classifier: Environment :: Win32 (MS Windows)
Classifier: License :: OSI Approved :: MIT License
Classifier: Operating System :: Microsoft :: Windows :: Windows XP
Classifier: Operating System :: Microsoft :: Windows :: Windows 7
Classifier: Programming Language :: Python
Classifier: Programming Language :: Python :: 2.7
Classifier: Programming Language :: Python :: 3.3
Classifier: Programming Language :: Python :: 3.4
Classifier: Topic :: Scientific/Engineering
